workbenchdata_pandas-0.24.0a3.dist-info/top_level.txt
workbenchdata_pandas-0.24.0a3.dist-info/RECORD
workbenchdata_pandas-0.24.0a3.dist-info/METADATA
workbenchdata_pandas-0.24.0a3.dist-info/WHEEL
pandas/conftest.py
pandas/testing.py
pandas/__init__.py
pandas/lib.py
pandas/_version.py
pandas/json.py
pandas/tslib.py
pandas/parser.py
pandas/plotting/_converter.py
pandas/plotting/_tools.py
pandas/plotting/_timeseries.py
pandas/plotting/_core.py
pandas/plotting/__init__.py
pandas/plotting/_style.py
pandas/plotting/_compat.py
pandas/plotting/_misc.py
pandas/util/testing.py
pandas/util/decorators.py
pandas/util/__init__.py
pandas/util/_tester.py
pandas/util/_print_versions.py
pandas/util/_depr_module.py
pandas/util/_decorators.py
pandas/util/_move.cpython-36m-x86_64-linux-gnu.so
pandas/util/_test_decorators.py
pandas/util/_doctools.py
pandas/util/_validators.py
pandas/formats/__init__.py
pandas/formats/style.py
pandas/computation/__init__.py
pandas/computation/expressions.py
pandas/tools/merge.py
pandas/tools/__init__.py
pandas/tools/plotting.py
pandas/errors/__init__.py
pandas/api/__init__.py
pandas/api/extensions/__init__.py
pandas/api/types/__init__.py
pandas/tseries/holiday.py
pandas/tseries/converter.py
pandas/tseries/api.py
pandas/tseries/__init__.py
pandas/tseries/plotting.py
pandas/tseries/frequencies.py
pandas/tseries/offsets.py
pandas/compat/pickle_compat.py
pandas/compat/__init__.py
pandas/compat/chainmap.py
pandas/compat/chainmap_impl.py
pandas/compat/numpy/__init__.py
pandas/compat/numpy/function.py
pandas/types/common.py
pandas/types/__init__.py
pandas/types/concat.py
pandas/_libs/missing.cpython-36m-x86_64-linux-gnu.so
pandas/_libs/internals.cpython-36m-x86_64-linux-gnu.so
pandas/_libs/parsers.cpython-36m-x86_64-linux-gnu.so
pandas/_libs/indexing.cpython-36m-x86_64-linux-gnu.so
pandas/_libs/hashtable.cpython-36m-x86_64-linux-gnu.so
pandas/_libs/skiplist.cpython-36m-x86_64-linux-gnu.so
pandas/_libs/hashing.cpython-36m-x86_64-linux-gnu.so
pandas/_libs/testing.cpython-36m-x86_64-linux-gnu.so
pandas/_libs/index.cpython-36m-x86_64-linux-gnu.so
pandas/_libs/__init__.py
