Metadata-Version: 2.1
Name: workbenchdata-pandas
Version: 0.24.0a3
Summary: Powerful data structures for data analysis, time series, and statistics
Home-page: http://pandas.pydata.org
Maintainer: The PyData Development Team
Maintainer-email: pydata@googlegroups.com
License: BSD
Platform: any
Classifier: Development Status :: 5 - Production/Stable
Classifier: Environment :: Console
Classifier: Operating System :: OS Independent
Classifier: Intended Audience :: Science/Research
Classifier: Programming Language :: Python
Classifier: Programming Language :: Python :: 2
Classifier: Programming Language :: Python :: 3
Classifier: Programming Language :: Python :: 2.7
Classifier: Programming Language :: Python :: 3.5
Classifier: Programming Language :: Python :: 3.6
Classifier: Programming Language :: Python :: 3.7
Classifier: Programming Language :: Cython
Classifier: Topic :: Scientific/Engineering
Requires-Python: >=2.7,!=3.0.*,!=3.1.*,!=3.2.*,!=3.3.*,!=3.4.*
Requires-Dist: python-dateutil (>=2.5.0)
Requires-Dist: pytz (>=2011k)
Requires-Dist: numpy (>=1.9.0)
